{
    "data": [
        {
            "id": 1,
            "benner": "HALAMAN 1",
            "title": "Halaman Character",
            "description": "Website Yang Berisi Informasi Seputar Valorant"
        },
        {
            "id": 2,
            "benner": "HALAMAN 2",
            "title": "Halaman Weapon",
            "description": "Website Yang Berisi Informasi Seputar Valorant"
        },
        {
            "id": 3,
            "benner": "HALAMAN 3",
            "title": "Halaman Map",
            "description": "Website Yang Berisi Informasi Seputar Valorant"
        }
    ]
}